filesystem_autocomplete/__init__.py
filesystem_autocomplete/filesystem_autocomplete.py
filesystem_autocomplete/tests/test_filesystem_autocomplete.py
filesystem_autocomplete-0.1.0.dist-info/LICENSE
filesystem_autocomplete-0.1.0.dist-info/METADATA
filesystem_autocomplete-0.1.0.dist-info/WHEEL
filesystem_autocomplete-0.1.0.dist-info/top_level.txt
filesystem_autocomplete-0.1.0.dist-info/RECORD
