Metadata-Version: 2.1
Name: filesystem-autocomplete
Version: 0.1.0
Summary: recursive filesystem object
Author-email: Chris Havlin <chris.havlin@gmail.com>
Project-URL: Homepage, https://github.com/chrishavlin/filesystem_autocomplete
Project-URL: Bug Tracker, https://github.com/chrishavlin/filesystem_autocomplete/issues
Classifier: Programming Language :: Python :: 3
Classifier: License :: OSI Approved :: MIT License
Classifier: Operating System :: OS Independent
Requires-Python: >=3.9
License-File: LICENSE
